astrbot/__init__.py
astrbot/api/__init__.py
astrbot/api/all.py
astrbot/api/message_components.py
astrbot/api/event/__init__.py
astrbot/api/event/filter/__init__.py
astrbot/api/platform/__init__.py
astrbot/api/provider/__init__.py
astrbot/api/star/__init__.py
astrbot/api/util/__init__.py
astrbot/cli/__init__.py
astrbot/cli/__main__.py
astrbot/cli/commands/__init__.py
astrbot/cli/commands/cmd_conf.py
astrbot/cli/commands/cmd_init.py
astrbot/cli/commands/cmd_plug.py
astrbot/cli/commands/cmd_run.py
astrbot/cli/utils/__init__.py
astrbot/cli/utils/basic.py
astrbot/cli/utils/plugin.py
astrbot/cli/utils/version_comparator.py
astrbot/core/__init__.py
astrbot/core/conversation_mgr.py
astrbot/core/core_lifecycle.py
astrbot/core/event_bus.py
astrbot/core/file_token_service.py
astrbot/core/initial_loader.py
astrbot/core/log.py
astrbot/core/updator.py
astrbot/core/zip_updator.py
astrbot/core/config/__init__.py
astrbot/core/config/astrbot_config.py
astrbot/core/config/default.py
astrbot/core/db/__init__.py
astrbot/core/db/po.py
astrbot/core/db/sqlite.py
astrbot/core/pipeline/__init__.py
astrbot/core/pipeline/context.py
astrbot/core/pipeline/scheduler.py
astrbot/core/pipeline/stage.py
astrbot/core/platform/__init__.py
astrbot/core/platform/astr_message_event.py
astrbot/core/platform/astrbot_message.py
astrbot/core/platform/manager.py
astrbot/core/platform/message_type.py
astrbot/core/platform/platform.py
astrbot/core/platform/platform_metadata.py
astrbot/core/platform/register.py
astrbot/core/provider/__init__.py
astrbot/core/provider/entites.py
astrbot/core/provider/entities.py
astrbot/core/provider/func_tool_manager.py
astrbot/core/provider/manager.py
astrbot/core/provider/provider.py
astrbot/core/provider/register.py
astrbot/core/star/__init__.py
astrbot/core/star/config.py
astrbot/core/star/context.py
astrbot/core/star/star.py
astrbot/core/star/star_handler.py
astrbot/core/star/star_manager.py
astrbot/core/star/star_tools.py
astrbot/core/star/updator.py
mseep_astrbot-3.5.18.dist-info/licenses/LICENSE
mseep_astrbot-3.5.18.dist-info/METADATA
mseep_astrbot-3.5.18.dist-info/WHEEL
mseep_astrbot-3.5.18.dist-info/top_level.txt
mseep_astrbot-3.5.18.dist-info/RECORD
