Metadata-Version: 2.4
Name: mseep-AstrBot
Version: 3.5.18
Summary: 易上手的多平台 LLM 聊天机器人及开发框架
Home-page: 
Author: mseep
Author-email: support@skydeck.ai
Maintainer: mseep
Maintainer-email: support@skydeck.ai
Keywords: mseep
Classifier: Programming Language :: Python :: 3
Classifier: License :: OSI Approved :: MIT License
Classifier: Operating System :: OS Independent
Requires-Python: >=3.6
License-File: LICENSE
Requires-Dist: aiocqhttp>=1.4.4
Requires-Dist: aiodocker>=0.24.0
Requires-Dist: aiohttp>=3.11.18
Requires-Dist: aiosqlite>=0.21.0
Requires-Dist: anthropic>=0.51.0
Requires-Dist: apscheduler>=3.11.0
Requires-Dist: beautifulsoup4>=4.13.4
Requires-Dist: certifi>=2025.4.26
Requires-Dist: chardet~=5.1.0
Requires-Dist: colorlog>=6.9.0
Requires-Dist: cryptography>=44.0.3
Requires-Dist: dashscope>=1.23.2
Requires-Dist: defusedxml>=0.7.1
Requires-Dist: dingtalk-stream>=0.22.1
Requires-Dist: docstring-parser>=0.16
Requires-Dist: faiss-cpu>=1.10.0
Requires-Dist: filelock>=3.18.0
Requires-Dist: google-genai>=1.14.0
Requires-Dist: googlesearch-python>=1.3.0
Requires-Dist: lark-oapi>=1.4.15
Requires-Dist: lxml-html-clean>=0.4.2
Requires-Dist: mcp>=1.8.0
Requires-Dist: nh3>=0.2.21
Requires-Dist: openai>=1.78.0
Requires-Dist: ormsgpack>=1.9.1
Requires-Dist: pillow>=11.2.1
Requires-Dist: pip>=25.1.1
Requires-Dist: psutil>=5.8.0
Requires-Dist: py-cord>=2.6.1
Requires-Dist: pydantic~=2.10.3
Requires-Dist: pydub>=0.25.1
Requires-Dist: pyjwt>=2.10.1
Requires-Dist: python-telegram-bot>=22.0
Requires-Dist: qq-botpy>=1.2.1
Requires-Dist: quart>=0.20.0
Requires-Dist: readability-lxml>=0.8.4.1
Requires-Dist: silk-python>=0.2.6
Requires-Dist: slack-sdk>=3.35.0
Requires-Dist: telegramify-markdown>=0.5.1
Requires-Dist: watchfiles>=1.0.5
Requires-Dist: websockets>=15.0.1
Requires-Dist: wechatpy>=1.8.18
Dynamic: author
Dynamic: author-email
Dynamic: classifier
Dynamic: description
Dynamic: description-content-type
Dynamic: keywords
Dynamic: license-file
Dynamic: maintainer
Dynamic: maintainer-email
Dynamic: requires-dist
Dynamic: requires-python
Dynamic: summary
